{
  "/-deb": {
    "component": "c4f5d8e4",
    "config": "5e9f5e1a"
  },
  "/blog-f8e": {
    "component": "a6aa9e1f",
    "sidebar": "c6783177",
    "items": [
      {
        "content": "af172acd"
      },
      {
        "content": "3570154c"
      },
      {
        "content": "8e9f0a8a"
      }
    ],
    "metadata": "b2b675dd"
  },
  "/blog/hello-world-8e5": {
    "component": "ccc49370",
    "sidebar": "c6783177",
    "content": "d610846f"
  },
  "/blog/hola-fee": {
    "component": "ccc49370",
    "sidebar": "c6783177",
    "content": "bdd709f1"
  },
  "/blog/tags-5fa": {
    "component": "01a85c17",
    "sidebar": "c6783177",
    "tags": "a7023ddc"
  },
  "/blog/tags/docusaurus-5d1": {
    "component": "6875c492",
    "sidebar": "c6783177",
    "items": [
      {
        "content": "af172acd"
      },
      {
        "content": "3570154c"
      },
      {
        "content": "8e9f0a8a"
      }
    ],
    "metadata": "a80da1cf"
  },
  "/blog/tags/facebook-016": {
    "component": "6875c492",
    "sidebar": "c6783177",
    "items": [
      {
        "content": "af172acd"
      }
    ],
    "metadata": "031793e1"
  },
  "/blog/tags/hello-7f2": {
    "component": "6875c492",
    "sidebar": "c6783177",
    "items": [
      {
        "content": "af172acd"
      },
      {
        "content": "3570154c"
      }
    ],
    "metadata": "30a24c52"
  },
  "/blog/tags/hola-e92": {
    "component": "6875c492",
    "sidebar": "c6783177",
    "items": [
      {
        "content": "8e9f0a8a"
      }
    ],
    "metadata": "e16015ca"
  },
  "/blog/welcome-c5a": {
    "component": "ccc49370",
    "sidebar": "c6783177",
    "content": "2868cdab"
  },
  "/docs-327": {
    "component": "1be78505",
    "versionMetadata": "935f2afb"
  },
  "/docs/about/AboutMe-416": {
    "component": "17896441",
    "content": "ee8a3c07"
  },
  "/docs/about/AboutThisPage-642": {
    "component": "17896441",
    "content": "cd02694c"
  },
  "/docs/portfolio/Portfolio-a8f": {
    "component": "17896441",
    "content": "12f93252"
  },
  "/docs/resume/Resume-f12": {
    "component": "17896441",
    "content": "5cc6b50b"
  }
}